llama_index/packs/raft_dataset/__init__.py
llama_index/packs/raft_dataset/base.py
llama_index_packs_raft_dataset-0.4.1.dist-info/METADATA
llama_index_packs_raft_dataset-0.4.1.dist-info/WHEEL
llama_index_packs_raft_dataset-0.4.1.dist-info/licenses/LICENSE
llama_index_packs_raft_dataset-0.4.1.dist-info/RECORD
