Metadata-Version: 2.4
Name: llama-index-packs-raft-dataset
Version: 0.4.1
Summary: llama-index packs RAFT Dataset paper implementation
Author-email: Ravi Theja <ravi03071991@gmail.com>
Maintainer: ravi-theja
License-Expression: MIT
License-File: LICENSE
Keywords: finetuning,raft,raft_dataset
Requires-Python: <4.0,>=3.9
Requires-Dist: datasets<3,>=2.18.0
Requires-Dist: llama-index-core<0.15,>=0.13.0
Requires-Dist: llama-index-embeddings-openai<0.6,>=0.5.0
Requires-Dist: llama-index-llms-openai<0.6,>=0.5.0
